jdvv/__init__.py
jdvv/components.py
jdvv/utils.py
jdvv/viewer.py
jdvv-0.0.2.dist-info/LICENSE
jdvv-0.0.2.dist-info/METADATA
jdvv-0.0.2.dist-info/WHEEL
jdvv-0.0.2.dist-info/top_level.txt
jdvv-0.0.2.dist-info/RECORD
