Metadata-Version: 2.1
Name: jdvv
Version: 0.0.2
Summary: Jupyter Dash Viewer for VTK
Home-page: https://github.com/ericbdaniels/jupyter-dash-vtk-viewer
Author: Eric Daniels
License: MIT
Platform: UNKNOWN
Requires-Python: >=3.6
Requires-Dist: dash-vtk
Requires-Dist: vtk
Requires-Dist: plotly
Requires-Dist: dash
Requires-Dist: dash-daq
Requires-Dist: dash-bootstrap-components
Requires-Dist: jupyter-dash
